otime/__init__.py
otime/analyzer.py
otime/utils.py
otime-0.1.3.dist-info/LICENSE
otime-0.1.3.dist-info/METADATA
otime-0.1.3.dist-info/WHEEL
otime-0.1.3.dist-info/top_level.txt
otime-0.1.3.dist-info/RECORD
