Metadata-Version: 2.1
Name: otime
Version: 0.1.3
Summary: A package for analyzing time complexity of functions
Home-page: https://github.com/MeatyAri/otime
Author: Arian Rahmatpour
Author-email: meatyari@proton.me
Classifier: Programming Language :: Python :: 3
Classifier: License :: OSI Approved :: MIT License
Classifier: Operating System :: OS Independent
Classifier: Development Status :: 3 - Alpha
Classifier: Intended Audience :: Developers
Classifier: Topic :: Software Development :: Libraries :: Python Modules
Requires-Python: >=3.8
License-File: LICENSE
Requires-Dist: numpy>=1.20.0
Requires-Dist: matplotlib>=3.3.0
